soda_jedi_ls/__init__.py
soda_jedi_ls/cli.py
soda_jedi_ls/constants.py
soda_jedi_ls/initialization_options.py
soda_jedi_ls/jedi_utils.py
soda_jedi_ls/py.typed
soda_jedi_ls/pygls_utils.py
soda_jedi_ls/server.py
soda_jedi_ls/text_edit_utils.py
soda_jedi_ls/type_map.py
soda_jedi_ls-2025.3.14.2.dist-info/METADATA
soda_jedi_ls-2025.3.14.2.dist-info/WHEEL
soda_jedi_ls-2025.3.14.2.dist-info/entry_points.txt
soda_jedi_ls-2025.3.14.2.dist-info/licenses/LICENSE
soda_jedi_ls-2025.3.14.2.dist-info/RECORD
